dfimage.py
dfimage-1.0.1.dist-info/LICENSE
dfimage-1.0.1.dist-info/METADATA
dfimage-1.0.1.dist-info/WHEEL
dfimage-1.0.1.dist-info/entry_points.txt
dfimage-1.0.1.dist-info/top_level.txt
dfimage-1.0.1.dist-info/RECORD
